{
  "data":[
    {
      "cordinates": [
        {
          "start": [510, 949],
          "end": [539, 955]
        },
        {
          "start": [499, 913],
          "end": [550, 914]
        },
        {
          "start": [493, 920],
          "end": [494, 970]
        },
        {
          "start": [555, 919],
          "end": [556, 968]
        },
        {
          "start": [519, 925],
          "end": [530, 934]
        } 
      ],
      "color": "#FFD635"
    },
    {
        "cordinates": [
        {
          "start": [498, 931 ],
          "end": [514, 936]
        }
      ],
      "color": "#000000"
    },
    {
        "cordinates": [
        {
          "start": [536, 932],
          "end": [547, 937 ]
        }
      ],
      "color": "#000000"
    }
  ]
}
